latentis/__init__.py
latentis/_version.py
latentis/nexus.py
latentis/types.py
latentis/utils.py
latentis/benchmark/__init__.py
latentis/benchmark/resolver.py
latentis/benchmark/task.py
latentis/correspondence/__init__.py
latentis/correspondence/_base.py
latentis/correspondence/correspondence.py
latentis/correspondence/gen_correspondences.py
latentis/data/__init__.py
latentis/data/dataset.py
latentis/data/encode.py
latentis/data/processor.py
latentis/data/text_encoding.py
latentis/data/train.py
latentis/data/utils.py
latentis/measure/__init__.py
latentis/measure/_abstract.py
latentis/measure/_metrics.py
latentis/measure/base.py
latentis/measure/cka.py
latentis/measure/svcca.py
latentis/measure/functional/__init__.py
latentis/measure/functional/cka.py
latentis/measure/functional/svcca.py
latentis/nn/__init__.py
latentis/nn/_base.py
latentis/nn/decoders.py
latentis/nn/encoders.py
latentis/project/relative.py
latentis/sample/__init__.py
latentis/sample/sampling.py
latentis/serialize/__init__.py
latentis/serialize/disk_index.py
latentis/serialize/io_utils.py
latentis/space/__init__.py
latentis/space/_base.py
latentis/space/search.py
latentis/space/vector_source.py
latentis/transform/__init__.py
latentis/transform/_abstract.py
latentis/transform/base.py
latentis/transform/dim_matcher.py
latentis/transform/functional.py
latentis/transform/projection.py
latentis/transform/translate/__init__.py
latentis/transform/translate/aligner.py
latentis/transform/translate/functional.py
latentis/visualize/__init__.py
latentis-0.0.8.dist-info/LICENSE
latentis-0.0.8.dist-info/METADATA
latentis-0.0.8.dist-info/WHEEL
latentis-0.0.8.dist-info/top_level.txt
latentis-0.0.8.dist-info/RECORD
