Metadata-Version: 2.1
Name: latentis
Version: 0.0.8
Summary: A Python package for analyzing and transforming neural latent spaces.
Home-page: https://github.com/flegyas/latentis
Author: Valentino Maiorca
Author-email: valentino@maiorca.xyz
License: MIT Licence
Keywords: python
Classifier: Development Status :: 3 - Alpha
Classifier: Intended Audience :: Developers
Classifier: Intended Audience :: Science/Research
Classifier: Topic :: Scientific/Engineering :: Artificial Intelligence
Classifier: Topic :: Scientific/Engineering :: Information Analysis
Classifier: Topic :: Scientific/Engineering :: Mathematics
Classifier: Topic :: Scientific/Engineering :: Visualization
Classifier: License :: OSI Approved :: MIT License
Classifier: Programming Language :: Python :: 3.8
Classifier: Programming Language :: Python :: 3.9
Classifier: Programming Language :: Python :: 3.10
License-File: LICENSE
Requires-Dist: torchmetrics
Requires-Dist: scikit-learn
Requires-Dist: backports.strenum
Requires-Dist: python-dotenv
Requires-Dist: GitPython
Requires-Dist: matplotlib
Requires-Dist: faiss-cpu
Requires-Dist: pandas
Requires-Dist: fire
Requires-Dist: lightning
Provides-Extra: data
Requires-Dist: transformers ; extra == 'data'
Requires-Dist: datasets ; extra == 'data'
Requires-Dist: torchvision ; extra == 'data'
Provides-Extra: dev
Requires-Dist: black ; extra == 'dev'
Requires-Dist: flake8 ; extra == 'dev'
Requires-Dist: isort ; extra == 'dev'
Requires-Dist: pre-commit ; extra == 'dev'
Requires-Dist: bandit ; extra == 'dev'
Requires-Dist: mkdocs ; extra == 'dev'
Requires-Dist: mkdocs-material ; extra == 'dev'
Requires-Dist: mike ; extra == 'dev'
Requires-Dist: pytest ; extra == 'dev'
Requires-Dist: pytest-cov ; extra == 'dev'
Requires-Dist: transformers ; extra == 'dev'
Requires-Dist: datasets ; extra == 'dev'
Requires-Dist: torchvision ; extra == 'dev'
Provides-Extra: docs
Requires-Dist: mkdocs ; extra == 'docs'
Requires-Dist: mkdocs-material ; extra == 'docs'
Requires-Dist: mike ; extra == 'docs'
Provides-Extra: test
Requires-Dist: pytest ; extra == 'test'
Requires-Dist: pytest-cov ; extra == 'test'
